powerdns_migrator/__init__.py
powerdns_migrator/__main__.py
powerdns_migrator/async_client.py
powerdns_migrator/async_migrator.py
powerdns_migrator/cli.py
powerdns_migrator/config.py
powerdns_migrator/errors.py
powerdns_migrator/utils.py
powerdns_migrator-0.1.0.dist-info/licenses/LICENSE
powerdns_migrator-0.1.0.dist-info/METADATA
powerdns_migrator-0.1.0.dist-info/WHEEL
powerdns_migrator-0.1.0.dist-info/entry_points.txt
powerdns_migrator-0.1.0.dist-info/top_level.txt
powerdns_migrator-0.1.0.dist-info/RECORD
