Metadata-Version: 2.4
Name: powerdns-migrator
Version: 0.1.0
Summary: CLI tool and library to migrate PowerDNS zones between servers
Author: Deividas Raila
License: MIT License
Project-URL: Homepage, https://github.com/railadeividas/powerdns-migrator
Project-URL: Repository, https://github.com/railadeividas/powerdns-migrator
Keywords: powerdns,dns,migration,pdns
Classifier: License :: OSI Approved :: MIT License
Classifier: Programming Language :: Python :: 3
Classifier: Programming Language :: Python :: 3 :: Only
Classifier: Programming Language :: Python :: 3.10
Classifier: Programming Language :: Python :: 3.11
Classifier: Programming Language :: Python :: 3.12
Classifier: Operating System :: OS Independent
Requires-Python: >=3.10
License-File: LICENSE
Requires-Dist: aiohttp>=3.9
Dynamic: license-file
